datasette_tail/__init__.py
datasette_tail-0.1a2.dist-info/licenses/LICENSE
datasette_tail-0.1a2.dist-info/METADATA
datasette_tail-0.1a2.dist-info/WHEEL
datasette_tail-0.1a2.dist-info/entry_points.txt
datasette_tail-0.1a2.dist-info/top_level.txt
datasette_tail-0.1a2.dist-info/RECORD
