Metadata-Version: 2.4
Name: datasette-tail
Version: 0.1a2
Summary: Tools for tailing your database
Author: Simon Willison
License-Expression: Apache-2.0
Project-URL: Homepage, https://github.com/datasette/datasette-tail
Project-URL: Changelog, https://github.com/datasette/datasette-tail/releases
Project-URL: Issues, https://github.com/datasette/datasette-tail/issues
Project-URL: CI, https://github.com/datasette/datasette-tail/actions
Classifier: Framework :: Datasette
Requires-Python: >=3.10
License-File: LICENSE
Requires-Dist: datasette>=1.0a20
Requires-Dist: dictdiffer
Provides-Extra: test
Requires-Dist: pytest; extra == "test"
Requires-Dist: pytest-asyncio; extra == "test"
Dynamic: license-file
